azure_custom_tools/__init__.py
azure_custom_tools/tools/__init__.py
azure_custom_tools/tools/first_tool.py
azure_custom_tools/tools/utils.py
azure_custom_tools/yamls/first_tool.yaml
tests/__init__.py
tests/test_first_tool.py
azure_custom_tools-0.0.2.dist-info/METADATA
azure_custom_tools-0.0.2.dist-info/WHEEL
azure_custom_tools-0.0.2.dist-info/entry_points.txt
azure_custom_tools-0.0.2.dist-info/top_level.txt
azure_custom_tools-0.0.2.dist-info/RECORD
