Metadata-Version: 2.1
Name: azure-custom-tools
Version: 0.0.2
Summary: This is my tools package
